{
  "pid": 143,
  "messageId": 14300,
  "fid": 36,
  "lightDistance": 0,
  "lightIntensity": 0,
  "flags": -1610612728,
  "extendedFlags": 41478,
  "sid": -1,
  "type": 3,
  "typeName": "weapon",
  "data": {
    "animationCode": 1,
    "minDamage": 5,
    "maxDamage": 8,
    "damageType": 2200,
    "maxRange1": 117440626,
    "maxRange2": 805306368,
    "projectilePid": 117440512,
    "minStrength": 234881024,
    "actionPointCost1": 570425344,
    "actionPointCost2": 0,
    "criticalFailureType": 838860800,
    "perk": 16777215,
    "rounds": -16777216,
    "caliber": 83886080,
    "ammoTypePid": 100663296,
    "ammoCapacity": 0,
    "soundCode": 2
  },
  "material": 58,
  "size": 0,
  "weight": 5,
  "cost": 34,
  "inventoryFid": 6,
  "soundCode": 71
}