{
  "pid": 16777621,
  "messageId": 40500,
  "fid": 16777229,
  "lightDistance": 0,
  "lightIntensity": 0,
  "flags": 536870912,
  "extendedFlags": 24576,
  "sid": -1,
  "data": {
    "flags": -1,
    "baseStats": [
      14,
      1,
      0,
      9,
      6,
      9,
      2,
      4,
      10,
      6,
      42,
      10,
      10,
      0,
      4,
      250,
      12,
      3,
      6,
      0,
      0,
      0,
      0,
      0,
      0,
      0,
      0,
      0,
      0,
      0,
      0,
      0,
      0,
      0,
      18
    ],
    "bonusStats": [
      45,
      25,
      0,
      0,
      0,
      0,
      0,
      0,
      0,
      0,
      68,
      0,
      18,
      0,
      0,
      0,
      0,
      0,
      0,
      0,
      2,
      0,
      2,
      0,
      0,
      0,
      0,
      30,
      20,
      25,
      10,
      30,
      500,
      20,
      0
    ],
    "skills": [
      0,
      0,
      0,
      65,
      70,
      0,
      57,
      67,
      35,
      0,
      0,
      0,
      0,
      0,
      0,
      0,
      0,
      0
    ],
    "bodyType": 17,
    "experience": 20,
    "killType": 0,
    "damageType": 0
  },
  "headFid": 350,
  "aiPacket": 0,
  "team": 0
}